dsd/src/count_8.v
module count_8(
 input clk,
 input rstn,
 input dir,
 input load,
 input[7:0] in,
 output[7:0] out
);
reg[7:0] counter ;

always @(posedge clk or negedge rstn)
begin : count_pro
 if(!rstn)
  counter <= 8'h00 ;
 else begin
  if(load) 
   counter <= in ;
  else
   case(dir)
    1'b0 : counter <= counter - 1'b1;
    1'b1 : counter <= counter + 1'b1;
   endcase
 end
end

assign out = counter ;

endmodule

dsd/tb/count_tb.v
module count_tb();

reg clk;
reg rstn;
reg dir;
reg load;
reg[7:0] in;
wire[7:0] out;

count_8 UUT(.clk(clk), .rstn(rstn), .dir(dir), .load(load), .in(in), .out(out)) ;

initial begin
$dumpfile("count_out.vcd");
$dumpvars(0, count_tb);

clk = 0;
rstn = 0;
load = 0 ;
dir = 0;

#10;

dir = 1 ;
rstn = 1;

#200 ;
 
dir = 0;

#100 ;

load = 1;
in = 8'h26 ;

#10 load = 0 ;

#100 ;

rstn = 0 ;

#10;

$finish ;

end

always
 #5 clk = ~clk ;

endmodule

dsd/sim/count_out.vcd
$date
	Mon Aug 23 22:52:16 2021
$end
$version
	Icarus Verilog
$end
$timescale
	1s
$end
$scope module count_tb $end
$var wire 8 ! out [7:0] $end
$var reg 1 " clk $end
$var reg 1 # dir $end
$var reg 8 $ in [7:0] $end
$var reg 1 % load $end
$var reg 1 & rstn $end
$scope module UUT $end
$var wire 1 " clk $end
$var wire 1 # dir $end
$var wire 8 ' in [7:0] $end
$var wire 1 % load $end
$var wire 8 ( out [7:0] $end
$var wire 1 & rstn $end
$var reg 8 ) counter [7:0] $end
$scope begin count_pro $end
$upscope $end
$upscope $end
$upscope $end
$enddefinitions $end
#0
$dumpvars
b0 )
b0 (
bx '
0&
0%
bx $
0#
0"
b0 !
$end
#5
1"
#10
0"
1&
1#
#15
b1 !
b1 (
b1 )
1"
#20
0"
#25
b10 !
b10 (
b10 )
1"
#30
0"
#35
b11 !
b11 (
b11 )
1"
#40
0"
#45
b100 !
b100 (
b100 )
1"
#50
0"
#55
b101 !
b101 (
b101 )
1"
#60
0"
#65
b110 !
b110 (
b110 )
1"
#70
0"
#75
b111 !
b111 (
b111 )
1"
#80
0"
#85
b1000 !
b1000 (
b1000 )
1"
#90
0"
#95
b1001 !
b1001 (
b1001 )
1"
#100
0"
#105
b1010 !
b1010 (
b1010 )
1"
#110
0"
#115
b1011 !
b1011 (
b1011 )
1"
#120
0"
#125
b1100 !
b1100 (
b1100 )
1"
#130
0"
#135
b1101 !
b1101 (
b1101 )
1"
#140
0"
#145
b1110 !
b1110 (
b1110 )
1"
#150
0"
#155
b1111 !
b1111 (
b1111 )
1"
#160
0"
#165
b10000 !
b10000 (
b10000 )
1"
#170
0"
#175
b10001 !
b10001 (
b10001 )
1"
#180
0"
#185
b10010 !
b10010 (
b10010 )
1"
#190
0"
#195
b10011 !
b10011 (
b10011 )
1"
#200
0"
#205
b10100 !
b10100 (
b10100 )
1"
#210
0"
0#
#215
b10011 !
b10011 (
b10011 )
1"
#220
0"
#225
b10010 !
b10010 (
b10010 )
1"
#230
0"
#235
b10001 !
b10001 (
b10001 )
1"
#240
0"
#245
b10000 !
b10000 (
b10000 )
1"
#250
0"
#255
b1111 !
b1111 (
b1111 )
1"
#260
0"
#265
b1110 !
b1110 (
b1110 )
1"
#270
0"
#275
b1101 !
b1101 (
b1101 )
1"
#280
0"
#285
b1100 !
b1100 (
b1100 )
1"
#290
0"
#295
b1011 !
b1011 (
b1011 )
1"
#300
0"
#305
b1010 !
b1010 (
b1010 )
1"
#310
0"
b100110 $
b100110 '
1%
#315
b100110 !
b100110 (
b100110 )
1"
#320
0"
0%
#325
b100101 !
b100101 (
b100101 )
1"
#330
0"
#335
b100100 !
b100100 (
b100100 )
1"
#340
0"
#345
b100011 !
b100011 (
b100011 )
1"
#350
0"
#355
b100010 !
b100010 (
b100010 )
1"
#360
0"
#365
b100001 !
b100001 (
b100001 )
1"
#370
0"
#375
b100000 !
b100000 (
b100000 )
1"
#380
0"
#385
b11111 !
b11111 (
b11111 )
1"
#390
0"
#395
b11110 !
b11110 (
b11110 )
1"
#400
0"
#405
b11101 !
b11101 (
b11101 )
1"
#410
0"
#415
b11100 !
b11100 (
b11100 )
1"
#420
b0 !
b0 (
b0 )
0"
0&
