dsd/src/fsm_1.v
module fsm_1(
 input[3:0] din,
 input clk, 
 input rstn, 
 output reg out
);

parameter idle = 3'b000, s1 = 3'b001, s2 = 3'b010, s3 = 3'b011, s4 = 3'b100, s5 = 3'b101;

reg[2:0] ps, ns ;
reg[3:0] data ;

always @(posedge clk or negedge rstn)
begin : seq_logic
 if(!rstn) 
  ps <= idle ;
 else 
  ps <= ns ;
end

always @(posedge clk or negedge rstn)
begin : input_process
 if(!rstn)
  data <= 4'h0 ;
 else data <= din ;
end 

always @(din)
begin : comb_logic
out <= 1'b0 ;
 case(ps)
  idle : if(din == 4'h1)
  		  ns <= s1 ;
  		 else ns <= idle ;

  s1 : if(din == 4'h3)
        ns <= s2;
       else ns <= idle ;

  s2 : if(din == 4'h4)
   	    ns <= s3;
   	   else ns <= idle ;

  s3 : if(din == 4'h8)
   	    ns <= s4;
   	   else ns <= idle ;
  s4 : if(din == 4'hD)
   	    ns <= s5;
   	   else ns <= idle;
  s5 : if(din == 4'h9)
   	    out <= 1'b1 ;
   	   else ns <= idle ;

  default : ns <= idle ;
 endcase 
end 

endmodule

dsd/tb/fsm_1_tb.v
module fsm_tb();

reg[3:0] din ; 
reg clk ;
reg rstn;
wire out;

fsm_1 UUT(
 .din(din),
 .clk(clk),
 .rstn(rstn),
 .out(out)
);

initial begin

$dumpfile("fsm_1.vcd");
$dumpvars(0,fsm_tb);

 rstn = 0; 
 clk = 0;
 din = 0;

//state change test
  #10;
   rstn = 1;
  din = 4'h1 ;

  #10;
  din = 4'h3 ;

  #10;
  din = 4'h4 ;

  #10;
  din = 4'h8 ;

  #10;
  din = 4'hD ;

  #10;
  din = 4'h9 ;

//testing to idle

  #10;
  din = 4'h1;

  #10;
  din = 4'h3 ;

  #10;
  din = 4'h6 ;

//test for reset

  #10;
  din = 4'h1;
  rstn = 0;

  #10;
  din = 4'h3 ;
  

  $finish ;

end

always 
 #5 clk = ~clk ;

endmodule

dsd/sim/fsm_1.vcd
$date
	Sat Aug 21 02:20:58 2021
$end
$version
	Icarus Verilog
$end
$timescale
	1s
$end
$scope module fsm_tb $end
$var wire 1 ! out $end
$var reg 1 " clk $end
$var reg 4 # din [3:0] $end
$var reg 1 $ rstn $end
$scope module UUT $end
$var wire 1 " clk $end
$var wire 4 % din [3:0] $end
$var wire 1 $ rstn $end
$var reg 4 & data [3:0] $end
$var reg 3 ' ns [2:0] $end
$var reg 1 ! out $end
$var reg 3 ( ps [2:0] $end
$scope begin comb_logic $end
$upscope $end
$scope begin input_process $end
$upscope $end
$scope begin seq_logic $end
$upscope $end
$upscope $end
$upscope $end
$enddefinitions $end
#0
$dumpvars
b0 (
b0 '
b0 &
b0 %
0$
b0 #
0"
0!
$end
#5
1"
#10
b1 '
0"
b1 #
b1 %
1$
#15
b1 &
b1 (
1"
#20
b10 '
0"
b11 #
b11 %
#25
b11 &
b10 (
1"
#30
b11 '
0"
b100 #
b100 %
#35
b100 &
b11 (
1"
#40
b100 '
0"
b1000 #
b1000 %
#45
b1000 &
b100 (
1"
#50
b101 '
0"
b1101 #
b1101 %
#55
b1101 &
b101 (
1"
#60
1!
0"
b1001 #
b1001 %
#65
b1001 &
1"
#70
b0 '
0!
0"
b1 #
b1 %
#75
b1 &
b0 (
1"
#80
0"
b11 #
b11 %
#85
b11 &
1"
#90
0"
b110 #
b110 %
#95
b110 &
1"
#100
b0 &
b1 '
0"
0$
b1 #
b1 %
#105
1"
#110
b0 '
0"
b11 #
b11 %
