dsd/shift.v
module shift(
input clk,
input rstn,
input load, 
input dir,
input [7:0] LD,
output cout
);

reg [7:0] mem;

assign cout = dir?mem[0]:mem[7] ;


always @(posedge clk or negedge rstn)
begin
 if(!rstn)
  mem <= 8'h00;
 else begin
  if(load) 
   mem <= LD ;
  else mem <= mem ;
  case(dir)
   0 : mem <= mem<<1 ;
   1 : mem <= mem>>1 ;
  endcase
 end
end

endmodule

dsd/shift_tb.v
module shift_tb();

reg clk;
reg rstn;
reg load;
reg dir;
reg[7:0] LD ;
wire cout;

shift UUT(.clk(clk), .rstn(rstn), .load(load), .dir(dir), .LD(LD), .cout(cout));

initial begin

$dumpfile("shift_out.vcd");
$dumpvars(2,shift_tb);

 clk = 0 ;
 rstn = 0 ;
 load = 0;
 dir = 0 ;
 LD = 8'h00;
 
 #10;
 rstn = 1;

 LD = 8'h55 ;
 load = 1;
 dir = 0 ;

 #100;

 LD = 8'hAA ;
 load = 1;
 dir = 1;

 #100;
 
 LD = 8'hFF;
 load = 1;
 rstn = 0 ;
 
 #20 ;
 $finish;
end 

always 
 #5 clk = ~clk ;

endmodule

dsd/shift_out.vcd
$date
	Fri Aug 20 15:16:25 2021
$end
$version
	Icarus Verilog
$end
$timescale
	1s
$end
$scope module shift_tb $end
$var wire 1 ! cout $end
$var reg 8 " LD [7:0] $end
$var reg 1 # clk $end
$var reg 1 $ dir $end
$var reg 1 % load $end
$var reg 1 & rstn $end
$scope module UUT $end
$var wire 8 ' LD [7:0] $end
$var wire 1 # clk $end
$var wire 1 $ dir $end
$var wire 1 % load $end
$var wire 1 & rstn $end
$var wire 1 ! cout $end
$var reg 8 ( mem [7:0] $end
$upscope $end
$upscope $end
$enddefinitions $end
#0
$dumpvars
b0 (
b0 '
0&
0%
0$
0#
b0 "
0!
$end
#5
1#
#10
0#
b1010101 "
b1010101 '
1&
#15
b0 (
1#
1%
#20
0#
#25
b0 (
1#
#30
0#
#35
b0 (
1#
#40
0#
#45
b0 (
1#
#50
0#
#55
b0 (
1#
#60
0#
#65
b0 (
1#
#70
0#
#75
b0 (
1#
#80
0#
#85
b0 (
1#
#90
0#
#95
b0 (
1#
#100
0#
#105
b0 (
1#
#110
0#
#115
b0 (
1#
1$
b10101010 "
b10101010 '
#120
0#
#125
b0 (
1#
#130
0#
#135
b0 (
1#
#140
0#
#145
b0 (
1#
#150
0#
#155
b0 (
1#
#160
0#
#165
b0 (
1#
#170
0#
#175
b0 (
1#
#180
0#
#185
b0 (
1#
#190
0#
#195
b0 (
1#
#200
0#
#205
b0 (
1#
#210
0#
#215
1#
0&
b11111111 "
b11111111 '
